ai_harmonization/__init__.py
ai_harmonization/cde.py
ai_harmonization/harmonization_benchmark.py
ai_harmonization/interactive.py
ai_harmonization/jsonl.py
ai_harmonization/main.py
ai_harmonization/simple_data_model.py
ai_harmonization/utils.py
ai_harmonization/harmonization_approaches/__init__.py
ai_harmonization/harmonization_approaches/base.py
ai_harmonization/harmonization_approaches/embeddings.py
ai_harmonization/harmonization_approaches/similarity_inmem.py
ai_harmonization-0.3.2.dist-info/licenses/LICENSE
ai_harmonization-0.3.2.dist-info/METADATA
ai_harmonization-0.3.2.dist-info/WHEEL
ai_harmonization-0.3.2.dist-info/top_level.txt
ai_harmonization-0.3.2.dist-info/RECORD
