Metadata-Version: 2.4
Name: ai_harmonization
Version: 0.3.2
Summary: AI-backed harmonization framework
Requires-Python: <4.0.0,>=3.12
License-File: LICENSE
Requires-Dist: langchain-chroma>=0.2.5
Requires-Dist: langchain-community>=0.3.27
Requires-Dist: langchain-core>=0.3.72
Requires-Dist: langchain-huggingface>=0.3.1
Requires-Dist: pydantic>=2.11.7
Requires-Dist: sssom>=0.4.16
Requires-Dist: sssom-schema>=1.0.0
Requires-Dist: tqdm>=4.67.1
Requires-Dist: transformers>=4.57.1
Requires-Dist: itables>=2.4.4
Requires-Dist: numpy>=2.0.2
Requires-Dist: pandas>=2.2.2
Requires-Dist: requests>=2.32.4
Requires-Dist: ipython>=7.34.0
Requires-Dist: torch>=2.8.0
Requires-Dist: matplotlib>=3.10.0
Requires-Dist: chromadb>=1.0.0
Dynamic: license-file
